astrologic/__init__.py
astrologic/function_text.py
astrologic/decorators/__init__.py
astrologic/decorators/base.py
astrologic/decorators/if_switcher.py
astrologic/decorators/inline.py
astrologic/decorators/tail_recursion_optimization.py
astrologic-0.0.9.dist-info/LICENSE
astrologic-0.0.9.dist-info/METADATA
astrologic-0.0.9.dist-info/WHEEL
astrologic-0.0.9.dist-info/top_level.txt
astrologic-0.0.9.dist-info/RECORD
